ordercloud_mcp/__init__.py
ordercloud_mcp/server.py
ordercloud_mcp-2.1.0.dist-info/METADATA
ordercloud_mcp-2.1.0.dist-info/WHEEL
ordercloud_mcp-2.1.0.dist-info/entry_points.txt
ordercloud_mcp-2.1.0.dist-info/licenses/license
ordercloud_mcp-2.1.0.dist-info/RECORD
