Metadata-Version: 2.4
Name: ordercloud-mcp
Version: 2.1.0
Summary: MCP server for Order Cloud API integration
Project-URL: Homepage, https://github.com/yourusername/ordercloud-mcp
Project-URL: Repository, https://github.com/yourusername/ordercloud-mcp
Project-URL: Issues, https://github.com/yourusername/ordercloud-mcp/issues
Author-email: Devesh Soni <devesh.soni@thoughtswinsystems.com>
License: MIT
License-File: license
Keywords: api,mcp,ordercloud,server
Classifier: Development Status :: 4 - Beta
Classifier: Intended Audience :: Developers
Classifier: License :: OSI Approved :: MIT License
Classifier: Programming Language :: Python :: 3
Classifier: Programming Language :: Python :: 3.10
Classifier: Programming Language :: Python :: 3.11
Classifier: Programming Language :: Python :: 3.12
Requires-Python: >=3.10
Requires-Dist: httpx>=0.24.0
Requires-Dist: mcp>=1.0.0
Provides-Extra: dev
Requires-Dist: black>=23.0.0; extra == 'dev'
Requires-Dist: pytest-asyncio>=0.21.0; extra == 'dev'
Requires-Dist: pytest>=7.0.0; extra == 'dev'
Requires-Dist: ruff>=0.1.0; extra == 'dev'
